shiny_ketcher/__init__.py
shiny_ketcher/shiny_ketcher.py
shiny_ketcher/distjs/index.css
shiny_ketcher/distjs/index.js
shiny_ketcher-0.9.dist-info/LICENSE
shiny_ketcher-0.9.dist-info/METADATA
shiny_ketcher-0.9.dist-info/WHEEL
shiny_ketcher-0.9.dist-info/top_level.txt
shiny_ketcher-0.9.dist-info/RECORD
